{"data":{"visible_replies":3,"sort":{"date":{"title":"По дате","is_selected":true,"name":"date","href":"/"},"helpful":{"title":"Самые полезные","is_selected":false,"name":"helpful","href":"/?sort=helpful"},"from_buyer":{"title":"От купивших этот товар","is_selected":false,"name":"from_buyer","href":"/?sort=from_buyer"},"with_attachments":{"title":"С фото и видео","is_selected":false,"name":"with_attachments","href":"/?sort=with_attachments"}},"pages":{"count":6,"selected":2},"record":{"id":17406357,"href":"http://bt.rozetka.com.ua/philips_hr3556_00/p17406357/","fulltitle":"Блендер PHILIPS Avance Collection HR3556/00","users_rating":{"count_comments":60},"pl_comment_bonus_charge":0,"pl_comment_photo_bonus_charge":0,"pl_comment_video_bonus_charge":0,"disable_comments_attachments":false},"replies":{"40045728":[{"id":40464398,"usertitle":"Представитель компании Philips","mark":0,"percent_dignity":"0","count_voices":0,"count_positive_voices":0,"negative_vote_count":0,"text":"Добрый день, Тая! Благодарим Вас за вопрос. В данном блендере присутствует функция колки льда, поэтому с его помощью Вы можете обрабатывать замороженные фрукты.","dignity":"","shortcomings":"","from_buyer":false,"created":{"pop_date":"25 марта 2019","year":"2019","month":3,"day":"25"},"questions":{"combobox":[],"marks":[],"integer":[]},"attachments":{"images":[],"video":[]},"lightboxattachmentsjson":"[]","commentdatajson":"{\"id\":40464398,\"goods_id\":\"17406357\",\"user_title\":\"\\u041f\\u0440\\u0435\\u0434\\u0441\\u0442\\u0430\\u0432\\u0438\\u0442\\u0435\\u043b\\u044c \\u043a\\u043e\\u043c\\u043f\\u0430\\u043d\\u0438\\u0438 Philips\",\"created\":\"25 \\u043c\\u0430\\u0440\\u0442\\u0430 2019\",\"from_buyer\":false,\"mark\":0,\"text\":\"\\u0414\\u043e\\u0431\\u0440\\u044b\\u0439 \\u0434\\u0435\\u043d\\u044c, \\u0422\\u0430\\u044f! \\u0411\\u043b\\u0430\\u0433\\u043e\\u0434\\u0430\\u0440\\u0438\\u043c \\u0412\\u0430\\u0441 \\u0437\\u0430 \\u0432\\u043e\\u043f\\u0440\\u043e\\u0441. \\u0412 \\u0434\\u0430\\u043d\\u043d\\u043e\\u043c \\u0431\\u043b\\u0435\\u043d\\u0434\\u0435\\u0440\\u0435 \\u043f\\u0440\\u0438\\u0441\\u0443\\u0442\\u0441\\u0442\\u0432\\u0443\\u0435\\u0442 \\u0444\\u0443\\u043d\\u043a\\u0446\\u0438\\u044f \\u043a\\u043e\\u043b\\u043a\\u0438 \\u043b\\u044c\\u0434\\u0430, \\u043f\\u043e\\u044d\\u0442\\u043e\\u043c\\u0443 \\u0441 \\u0435\\u0433\\u043e \\u043f\\u043e\\u043c\\u043e\\u0449\\u044c\\u044e \\u0412\\u044b \\u043c\\u043e\\u0436\\u0435\\u0442\\u0435 \\u043e\\u0431\\u0440\\u0430\\u0431\\u0430\\u0442\\u044b\\u0432\\u0430\\u0442\\u044c \\u0437\\u0430\\u043c\\u043e\\u0440\\u043e\\u0436\\u0435\\u043d\\u043d\\u044b\\u0435 \\u0444\\u0440\\u0443\\u043a\\u0442\\u044b.\",\"dignity\":\"\",\"shortcomings\":\"\",\"positive\":\"0\",\"negative\":\"0\",\"replies\":[],\"marks\":[],\"questions\":[],\"created_iso\":\"2019-03-25T14:52:05+02:00\"}","is_vendor_comment":true,"vendor_logo":"https://i2.rozetka.ua/producers/9/9401.80x60.png"},{"id":41078781,"usertitle":"Вільвєталь Віайпі","mark":0,"percent_dignity":"0","count_voices":0,"count_positive_voices":0,"negative_vote_count":0,"text":"Дуже гарно вбиває усі ягоди окрім вовчих та собачих для таких придивітся краще до моделі Philips Avance Collection HR3652/00.","dignity":"","shortcomings":"","from_buyer":true,"created":{"pop_date":"10 апреля 2019","year":"2019","month":4,"day":"10"},"questions":{"combobox":[],"marks":[],"integer":[]},"attachments":{"images":[],"video":[]},"lightboxattachmentsjson":"[]","commentdatajson":"{\"id\":41078781,\"goods_id\":\"17406357\",\"user_title\":\"\\u0412\\u0456\\u043b\\u044c\\u0432\\u0454\\u0442\\u0430\\u043b\\u044c \\u0412\\u0456\\u0430\\u0439\\u043f\\u0456\",\"created\":\"10 \\u0430\\u043f\\u0440\\u0435\\u043b\\u044f 2019\",\"from_buyer\":true,\"mark\":0,\"text\":\"\\u0414\\u0443\\u0436\\u0435 \\u0433\\u0430\\u0440\\u043d\\u043e \\u0432\\u0431\\u0438\\u0432\\u0430\\u0454 \\u0443\\u0441\\u0456 \\u044f\\u0433\\u043e\\u0434\\u0438 \\u043e\\u043a\\u0440\\u0456\\u043c \\u0432\\u043e\\u0432\\u0447\\u0438\\u0445 \\u0442\\u0430 \\u0441\\u043e\\u0431\\u0430\\u0447\\u0438\\u0445 \\u0434\\u043b\\u044f \\u0442\\u0430\\u043a\\u0438\\u0445 \\u043f\\u0440\\u0438\\u0434\\u0438\\u0432\\u0456\\u0442\\u0441\\u044f \\u043a\\u0440\\u0430\\u0449\\u0435 \\u0434\\u043e \\u043c\\u043e\\u0434\\u0435\\u043b\\u0456 Philips Avance Collection HR3652\\/00.\",\"dignity\":\"\",\"shortcomings\":\"\",\"positive\":\"0\",\"negative\":\"0\",\"replies\":[],\"marks\":[],\"questions\":[],\"created_iso\":\"2019-04-10T16:23:31+03:00\"}","is_vendor_comment":false,"vendor_logo":""}],"42033598":[{"id":42038812,"usertitle":"Валя","mark":0,"percent_dignity":"0","count_voices":0,"count_positive_voices":0,"negative_vote_count":0,"text":"ниже отвечал представитель, <br />\n Согласно инструкции по эксплуатации, чаша блендера предназначена для: <br />\n- Перемешивания жидкостей, таких как молочные продукты, соусы, фруктовые соки, супы, напитки, коктейли, смузи.<br />\n- Перемешивания мягких продуктов, таких как жидкое тесто или майонез.<br />\n- Приготовления пюре из отварных продуктов, например, приготовления детского питания.<br />\n- Измельчения кубиков льда.","dignity":"","shortcomings":"","from_buyer":false,"created":{"pop_date":"9 мая 2019","year":"2019","month":5,"day":"09"},"questions":{"combobox":[],"marks":[],"integer":[]},"attachments":{"images":[],"video":[]},"lightboxattachmentsjson":"[]","commentdatajson":"{\"id\":42038812,\"goods_id\":\"17406357\",\"user_title\":\"\\u0412\\u0430\\u043b\\u044f\",\"created\":\"9 \\u043c\\u0430\\u044f 2019\",\"from_buyer\":false,\"mark\":0,\"text\":\"\\u043d\\u0438\\u0436\\u0435 \\u043e\\u0442\\u0432\\u0435\\u0447\\u0430\\u043b \\u043f\\u0440\\u0435\\u0434\\u0441\\u0442\\u0430\\u0432\\u0438\\u0442\\u0435\\u043b\\u044c, <br \\/>\\n \\u0421\\u043e\\u0433\\u043b\\u0430\\u0441\\u043d\\u043e \\u0438\\u043d\\u0441\\u0442\\u0440\\u0443\\u043a\\u0446\\u0438\\u0438 \\u043f\\u043e \\u044d\\u043a\\u0441\\u043f\\u043b\\u0443\\u0430\\u0442\\u0430\\u0446\\u0438\\u0438, \\u0447\\u0430\\u0448\\u0430 \\u0431\\u043b\\u0435\\u043d\\u0434\\u0435\\u0440\\u0430 \\u043f\\u0440\\u0435\\u0434\\u043d\\u0430\\u0437\\u043d\\u0430\\u0447\\u0435\\u043d\\u0430 \\u0434\\u043b\\u044f: <br \\/>\\n- \\u041f\\u0435\\u0440\\u0435\\u043c\\u0435\\u0448\\u0438\\u0432\\u0430\\u043d\\u0438\\u044f \\u0436\\u0438\\u0434\\u043a\\u043e\\u0441\\u0442\\u0435\\u0439, \\u0442\\u0430\\u043a\\u0438\\u0445 \\u043a\\u0430\\u043a \\u043c\\u043e\\u043b\\u043e\\u0447\\u043d\\u044b\\u0435 \\u043f\\u0440\\u043e\\u0434\\u0443\\u043a\\u0442\\u044b, \\u0441\\u043e\\u0443\\u0441\\u044b, \\u0444\\u0440\\u0443\\u043a\\u0442\\u043e\\u0432\\u044b\\u0435 \\u0441\\u043e\\u043a\\u0438, \\u0441\\u0443\\u043f\\u044b, \\u043d\\u0430\\u043f\\u0438\\u0442\\u043a\\u0438, \\u043a\\u043e\\u043a\\u0442\\u0435\\u0439\\u043b\\u0438, \\u0441\\u043c\\u0443\\u0437\\u0438.<br \\/>\\n- \\u041f\\u0435\\u0440\\u0435\\u043c\\u0435\\u0448\\u0438\\u0432\\u0430\\u043d\\u0438\\u044f \\u043c\\u044f\\u0433\\u043a\\u0438\\u0445 \\u043f\\u0440\\u043e\\u0434\\u0443\\u043a\\u0442\\u043e\\u0432, \\u0442\\u0430\\u043a\\u0438\\u0445 \\u043a\\u0430\\u043a \\u0436\\u0438\\u0434\\u043a\\u043e\\u0435 \\u0442\\u0435\\u0441\\u0442\\u043e \\u0438\\u043b\\u0438 \\u043c\\u0430\\u0439\\u043e\\u043d\\u0435\\u0437.<br \\/>\\n- \\u041f\\u0440\\u0438\\u0433\\u043e\\u0442\\u043e\\u0432\\u043b\\u0435\\u043d\\u0438\\u044f \\u043f\\u044e\\u0440\\u0435 \\u0438\\u0437 \\u043e\\u0442\\u0432\\u0430\\u0440\\u043d\\u044b\\u0445 \\u043f\\u0440\\u043e\\u0434\\u0443\\u043a\\u0442\\u043e\\u0432, \\u043d\\u0430\\u043f\\u0440\\u0438\\u043c\\u0435\\u0440, \\u043f\\u0440\\u0438\\u0433\\u043e\\u0442\\u043e\\u0432\\u043b\\u0435\\u043d\\u0438\\u044f \\u0434\\u0435\\u0442\\u0441\\u043a\\u043e\\u0433\\u043e \\u043f\\u0438\\u0442\\u0430\\u043d\\u0438\\u044f.<br \\/>\\n- \\u0418\\u0437\\u043c\\u0435\\u043b\\u044c\\u0447\\u0435\\u043d\\u0438\\u044f \\u043a\\u0443\\u0431\\u0438\\u043a\\u043e\\u0432 \\u043b\\u044c\\u0434\\u0430.\",\"dignity\":\"\",\"shortcomings\":\"\",\"positive\":\"0\",\"negative\":\"0\",\"replies\":[],\"marks\":[],\"questions\":[],\"created_iso\":\"2019-05-09T09:09:00+03:00\"}","is_vendor_comment":false,"vendor_logo":""}],"41841426":[{"id":42191865,"usertitle":"Представитель компании Philips","mark":0,"percent_dignity":"0","count_voices":0,"count_positive_voices":0,"negative_vote_count":0,"text":"Доброго дня, Тарасе! Так, аксесуар моделі CP6670, згідно з інструкцією, підходить для даної моделі блендера (https://www.download.p4c.philips.com/files/h/hr3556_00/hr3556_00_dfu_ukr.pdf).","dignity":"","shortcomings":"","from_buyer":false,"created":{"pop_date":"13 мая 2019","year":"2019","month":5,"day":"13"},"questions":{"combobox":[],"marks":[],"integer":[]},"attachments":{"images":[],"video":[]},"lightboxattachmentsjson":"[]","commentdatajson":"{\"id\":42191865,\"goods_id\":\"17406357\",\"user_title\":\"\\u041f\\u0440\\u0435\\u0434\\u0441\\u0442\\u0430\\u0432\\u0438\\u0442\\u0435\\u043b\\u044c \\u043a\\u043e\\u043c\\u043f\\u0430\\u043d\\u0438\\u0438 Philips\",\"created\":\"13 \\u043c\\u0430\\u044f 2019\",\"from_buyer\":false,\"mark\":0,\"text\":\"\\u0414\\u043e\\u0431\\u0440\\u043e\\u0433\\u043e \\u0434\\u043d\\u044f, \\u0422\\u0430\\u0440\\u0430\\u0441\\u0435! \\u0422\\u0430\\u043a, \\u0430\\u043a\\u0441\\u0435\\u0441\\u0443\\u0430\\u0440 \\u043c\\u043e\\u0434\\u0435\\u043b\\u0456 CP6670, \\u0437\\u0433\\u0456\\u0434\\u043d\\u043e \\u0437 \\u0456\\u043d\\u0441\\u0442\\u0440\\u0443\\u043a\\u0446\\u0456\\u0454\\u044e, \\u043f\\u0456\\u0434\\u0445\\u043e\\u0434\\u0438\\u0442\\u044c \\u0434\\u043b\\u044f \\u0434\\u0430\\u043d\\u043e\\u0457 \\u043c\\u043e\\u0434\\u0435\\u043b\\u0456 \\u0431\\u043b\\u0435\\u043d\\u0434\\u0435\\u0440\\u0430 (https:\\/\\/www.download.p4c.philips.com\\/files\\/h\\/hr3556_00\\/hr3556_00_dfu_ukr.pdf).\",\"dignity\":\"\",\"shortcomings\":\"\",\"positive\":\"0\",\"negative\":\"0\",\"replies\":[],\"marks\":[],\"questions\":[],\"created_iso\":\"2019-05-13T14:01:00+03:00\"}","is_vendor_comment":true,"vendor_logo":"https://i2.rozetka.ua/producers/9/9401.80x60.png"}],"42069166":[{"id":42478490,"usertitle":"Представитель компании Philips","mark":0,"percent_dignity":"0","count_voices":0,"count_positive_voices":0,"negative_vote_count":0,"text":"Добрый день, Александр! С помощью данного блендера можно обрабатывать сырые, твердые овощи (например морковь), но обращаем Ваше внимание на то, что при измельчении такого рода продуктов необходимо доливать немного воды.","dignity":"","shortcomings":"","from_buyer":false,"created":{"pop_date":"21 мая 2019","year":"2019","month":5,"day":"21"},"questions":{"combobox":[],"marks":[],"integer":[]},"attachments":{"images":[],"video":[]},"lightboxattachmentsjson":"[]","commentdatajson":"{\"id\":42478490,\"goods_id\":\"17406357\",\"user_title\":\"\\u041f\\u0440\\u0435\\u0434\\u0441\\u0442\\u0430\\u0432\\u0438\\u0442\\u0435\\u043b\\u044c \\u043a\\u043e\\u043c\\u043f\\u0430\\u043d\\u0438\\u0438 Philips\",\"created\":\"21 \\u043c\\u0430\\u044f 2019\",\"from_buyer\":false,\"mark\":0,\"text\":\"\\u0414\\u043e\\u0431\\u0440\\u044b\\u0439 \\u0434\\u0435\\u043d\\u044c, \\u0410\\u043b\\u0435\\u043a\\u0441\\u0430\\u043d\\u0434\\u0440! \\u0421 \\u043f\\u043e\\u043c\\u043e\\u0449\\u044c\\u044e \\u0434\\u0430\\u043d\\u043d\\u043e\\u0433\\u043e \\u0431\\u043b\\u0435\\u043d\\u0434\\u0435\\u0440\\u0430 \\u043c\\u043e\\u0436\\u043d\\u043e \\u043e\\u0431\\u0440\\u0430\\u0431\\u0430\\u0442\\u044b\\u0432\\u0430\\u0442\\u044c \\u0441\\u044b\\u0440\\u044b\\u0435, \\u0442\\u0432\\u0435\\u0440\\u0434\\u044b\\u0435 \\u043e\\u0432\\u043e\\u0449\\u0438 (\\u043d\\u0430\\u043f\\u0440\\u0438\\u043c\\u0435\\u0440 \\u043c\\u043e\\u0440\\u043a\\u043e\\u0432\\u044c), \\u043d\\u043e \\u043e\\u0431\\u0440\\u0430\\u0449\\u0430\\u0435\\u043c \\u0412\\u0430\\u0448\\u0435 \\u0432\\u043d\\u0438\\u043c\\u0430\\u043d\\u0438\\u0435 \\u043d\\u0430 \\u0442\\u043e, \\u0447\\u0442\\u043e \\u043f\\u0440\\u0438 \\u0438\\u0437\\u043c\\u0435\\u043b\\u044c\\u0447\\u0435\\u043d\\u0438\\u0438 \\u0442\\u0430\\u043a\\u043e\\u0433\\u043e \\u0440\\u043e\\u0434\\u0430 \\u043f\\u0440\\u043e\\u0434\\u0443\\u043a\\u0442\\u043e\\u0432 \\u043d\\u0435\\u043e\\u0431\\u0445\\u043e\\u0434\\u0438\\u043c\\u043e \\u0434\\u043e\\u043b\\u0438\\u0432\\u0430\\u0442\\u044c \\u043d\\u0435\\u043c\\u043d\\u043e\\u0433\\u043e \\u0432\\u043e\\u0434\\u044b.\",\"dignity\":\"\",\"shortcomings\":\"\",\"positive\":\"0\",\"negative\":\"0\",\"replies\":[],\"marks\":[],\"questions\":[],\"created_iso\":\"2019-05-21T14:40:45+03:00\"}","is_vendor_comment":true,"vendor_logo":"https://i2.rozetka.ua/producers/9/9401.80x60.png"}],"43121194":[{"id":43211266,"usertitle":"Представитель компании Philips","mark":0,"percent_dignity":"0","count_voices":0,"count_positive_voices":0,"negative_vote_count":0,"text":"Добрий день, Тарасе! Потужність даної моделі блендера становить 900 Вт.","dignity":"","shortcomings":"","from_buyer":false,"created":{"pop_date":"12 июня 2019","year":"2019","month":6,"day":"12"},"questions":{"combobox":[],"marks":[],"integer":[]},"attachments":{"images":[],"video":[]},"lightboxattachmentsjson":"[]","commentdatajson":"{\"id\":43211266,\"goods_id\":\"17406357\",\"user_title\":\"\\u041f\\u0440\\u0435\\u0434\\u0441\\u0442\\u0430\\u0432\\u0438\\u0442\\u0435\\u043b\\u044c \\u043a\\u043e\\u043c\\u043f\\u0430\\u043d\\u0438\\u0438 Philips\",\"created\":\"12 \\u0438\\u044e\\u043d\\u044f 2019\",\"from_buyer\":false,\"mark\":0,\"text\":\"\\u0414\\u043e\\u0431\\u0440\\u0438\\u0439 \\u0434\\u0435\\u043d\\u044c, \\u0422\\u0430\\u0440\\u0430\\u0441\\u0435! \\u041f\\u043e\\u0442\\u0443\\u0436\\u043d\\u0456\\u0441\\u0442\\u044c \\u0434\\u0430\\u043d\\u043e\\u0457 \\u043c\\u043e\\u0434\\u0435\\u043b\\u0456 \\u0431\\u043b\\u0435\\u043d\\u0434\\u0435\\u0440\\u0430 \\u0441\\u0442\\u0430\\u043d\\u043e\\u0432\\u0438\\u0442\\u044c 900 \\u0412\\u0442.\",\"dignity\":\"\",\"shortcomings\":\"\",\"positive\":\"0\",\"negative\":\"0\",\"replies\":[],\"marks\":[],\"questions\":[],\"created_iso\":\"2019-06-12T15:09:18+03:00\"}","is_vendor_comment":true,"vendor_logo":"https://i2.rozetka.ua/producers/9/9401.80x60.png"}],"43960927":[{"id":43988207,"usertitle":"Представитель компании Philips","mark":0,"percent_dignity":"0","count_voices":0,"count_positive_voices":0,"negative_vote_count":0,"text":"Доброго дня, Тарасе! Дякуємо за Ваше запитання. Пляшка On the Go виготовлена з пластику.","dignity":"","shortcomings":"","from_buyer":false,"created":{"pop_date":"17 июля 2019","year":"2019","month":7,"day":"17"},"questions":{"combobox":[],"marks":[],"integer":[]},"attachments":{"images":[],"video":[]},"lightboxattachmentsjson":"[]","commentdatajson":"{\"id\":43988207,\"goods_id\":\"17406357\",\"user_title\":\"\\u041f\\u0440\\u0435\\u0434\\u0441\\u0442\\u0430\\u0432\\u0438\\u0442\\u0435\\u043b\\u044c \\u043a\\u043e\\u043c\\u043f\\u0430\\u043d\\u0438\\u0438 Philips\",\"created\":\"17 \\u0438\\u044e\\u043b\\u044f 2019\",\"from_buyer\":false,\"mark\":0,\"text\":\"\\u0414\\u043e\\u0431\\u0440\\u043e\\u0433\\u043e \\u0434\\u043d\\u044f, \\u0422\\u0430\\u0440\\u0430\\u0441\\u0435! \\u0414\\u044f\\u043a\\u0443\\u0454\\u043c\\u043e \\u0437\\u0430 \\u0412\\u0430\\u0448\\u0435 \\u0437\\u0430\\u043f\\u0438\\u0442\\u0430\\u043d\\u043d\\u044f. \\u041f\\u043b\\u044f\\u0448\\u043a\\u0430 On the Go \\u0432\\u0438\\u0433\\u043e\\u0442\\u043e\\u0432\\u043b\\u0435\\u043d\\u0430 \\u0437 \\u043f\\u043b\\u0430\\u0441\\u0442\\u0438\\u043a\\u0443.\",\"dignity\":\"\",\"shortcomings\":\"\",\"positive\":\"0\",\"negative\":\"0\",\"replies\":[],\"marks\":[],\"questions\":[],\"created_iso\":\"2019-07-17T15:43:11+03:00\"}","is_vendor_comment":true,"vendor_logo":"https://i2.rozetka.ua/producers/9/9401.80x60.png"},{"id":43988208,"usertitle":"Представитель компании Philips","mark":0,"percent_dignity":"0","count_voices":0,"count_positive_voices":0,"negative_vote_count":0,"text":"Доброго дня, Тарасе! Дякуємо за Ваше запитання. Пляшка On the Go виготовлена з пластику.","dignity":"","shortcomings":"","from_buyer":false,"created":{"pop_date":"17 июля 2019","year":"2019","month":7,"day":"17"},"questions":{"combobox":[],"marks":[],"integer":[]},"attachments":{"images":[],"video":[]},"lightboxattachmentsjson":"[]","commentdatajson":"{\"id\":43988208,\"goods_id\":\"17406357\",\"user_title\":\"\\u041f\\u0440\\u0435\\u0434\\u0441\\u0442\\u0430\\u0432\\u0438\\u0442\\u0435\\u043b\\u044c \\u043a\\u043e\\u043c\\u043f\\u0430\\u043d\\u0438\\u0438 Philips\",\"created\":\"17 \\u0438\\u044e\\u043b\\u044f 2019\",\"from_buyer\":false,\"mark\":0,\"text\":\"\\u0414\\u043e\\u0431\\u0440\\u043e\\u0433\\u043e \\u0434\\u043d\\u044f, \\u0422\\u0430\\u0440\\u0430\\u0441\\u0435! \\u0414\\u044f\\u043a\\u0443\\u0454\\u043c\\u043e \\u0437\\u0430 \\u0412\\u0430\\u0448\\u0435 \\u0437\\u0430\\u043f\\u0438\\u0442\\u0430\\u043d\\u043d\\u044f. \\u041f\\u043b\\u044f\\u0448\\u043a\\u0430 On the Go \\u0432\\u0438\\u0433\\u043e\\u0442\\u043e\\u0432\\u043b\\u0435\\u043d\\u0430 \\u0437 \\u043f\\u043b\\u0430\\u0441\\u0442\\u0438\\u043a\\u0443.\",\"dignity\":\"\",\"shortcomings\":\"\",\"positive\":\"0\",\"negative\":\"0\",\"replies\":[],\"marks\":[],\"questions\":[],\"created_iso\":\"2019-07-17T15:43:17+03:00\"}","is_vendor_comment":true,"vendor_logo":"https://i2.rozetka.ua/producers/9/9401.80x60.png"}],"44010025":[{"id":44011894,"usertitle":"Представитель компании Philips","mark":0,"percent_dignity":"0","count_voices":0,"count_positive_voices":0,"negative_vote_count":0,"text":"Добрый день, Карина! Благодарим Вас за вопрос. С помощью данной модели блендера Вы можете делать ореховое молоко с добавлением воды. Также Вы можете обратить внимание на блендер модели HR2103/00, комплектация которого включает в себя  фильтр для приготовления соевого молока и фруктового сока без косточек и семян, при приготовлении с помощью фильтра все зёрна и кусочки кожуры остаются в фильтре.","dignity":"","shortcomings":"","from_buyer":false,"created":{"pop_date":"22 июля 2019","year":"2019","month":7,"day":"22"},"questions":{"combobox":[],"marks":[],"integer":[]},"attachments":{"images":[],"video":[]},"lightboxattachmentsjson":"[]","commentdatajson":"{\"id\":44011894,\"goods_id\":\"17406357\",\"user_title\":\"\\u041f\\u0440\\u0435\\u0434\\u0441\\u0442\\u0430\\u0432\\u0438\\u0442\\u0435\\u043b\\u044c \\u043a\\u043e\\u043c\\u043f\\u0430\\u043d\\u0438\\u0438 Philips\",\"created\":\"22 \\u0438\\u044e\\u043b\\u044f 2019\",\"from_buyer\":false,\"mark\":0,\"text\":\"\\u0414\\u043e\\u0431\\u0440\\u044b\\u0439 \\u0434\\u0435\\u043d\\u044c, \\u041a\\u0430\\u0440\\u0438\\u043d\\u0430! \\u0411\\u043b\\u0430\\u0433\\u043e\\u0434\\u0430\\u0440\\u0438\\u043c \\u0412\\u0430\\u0441 \\u0437\\u0430 \\u0432\\u043e\\u043f\\u0440\\u043e\\u0441. \\u0421 \\u043f\\u043e\\u043c\\u043e\\u0449\\u044c\\u044e \\u0434\\u0430\\u043d\\u043d\\u043e\\u0439 \\u043c\\u043e\\u0434\\u0435\\u043b\\u0438 \\u0431\\u043b\\u0435\\u043d\\u0434\\u0435\\u0440\\u0430 \\u0412\\u044b \\u043c\\u043e\\u0436\\u0435\\u0442\\u0435 \\u0434\\u0435\\u043b\\u0430\\u0442\\u044c \\u043e\\u0440\\u0435\\u0445\\u043e\\u0432\\u043e\\u0435 \\u043c\\u043e\\u043b\\u043e\\u043a\\u043e \\u0441 \\u0434\\u043e\\u0431\\u0430\\u0432\\u043b\\u0435\\u043d\\u0438\\u0435\\u043c \\u0432\\u043e\\u0434\\u044b. \\u0422\\u0430\\u043a\\u0436\\u0435 \\u0412\\u044b \\u043c\\u043e\\u0436\\u0435\\u0442\\u0435 \\u043e\\u0431\\u0440\\u0430\\u0442\\u0438\\u0442\\u044c \\u0432\\u043d\\u0438\\u043c\\u0430\\u043d\\u0438\\u0435 \\u043d\\u0430 \\u0431\\u043b\\u0435\\u043d\\u0434\\u0435\\u0440 \\u043c\\u043e\\u0434\\u0435\\u043b\\u0438 HR2103\\/00, \\u043a\\u043e\\u043c\\u043f\\u043b\\u0435\\u043a\\u0442\\u0430\\u0446\\u0438\\u044f \\u043a\\u043e\\u0442\\u043e\\u0440\\u043e\\u0433\\u043e \\u0432\\u043a\\u043b\\u044e\\u0447\\u0430\\u0435\\u0442 \\u0432 \\u0441\\u0435\\u0431\\u044f  \\u0444\\u0438\\u043b\\u044c\\u0442\\u0440 \\u0434\\u043b\\u044f \\u043f\\u0440\\u0438\\u0433\\u043e\\u0442\\u043e\\u0432\\u043b\\u0435\\u043d\\u0438\\u044f \\u0441\\u043e\\u0435\\u0432\\u043e\\u0433\\u043e \\u043c\\u043e\\u043b\\u043e\\u043a\\u0430 \\u0438 \\u0444\\u0440\\u0443\\u043a\\u0442\\u043e\\u0432\\u043e\\u0433\\u043e \\u0441\\u043e\\u043a\\u0430 \\u0431\\u0435\\u0437 \\u043a\\u043e\\u0441\\u0442\\u043e\\u0447\\u0435\\u043a \\u0438 \\u0441\\u0435\\u043c\\u044f\\u043d, \\u043f\\u0440\\u0438 \\u043f\\u0440\\u0438\\u0433\\u043e\\u0442\\u043e\\u0432\\u043b\\u0435\\u043d\\u0438\\u0438 \\u0441 \\u043f\\u043e\\u043c\\u043e\\u0449\\u044c\\u044e \\u0444\\u0438\\u043b\\u044c\\u0442\\u0440\\u0430 \\u0432\\u0441\\u0435 \\u0437\\u0451\\u0440\\u043d\\u0430 \\u0438 \\u043a\\u0443\\u0441\\u043e\\u0447\\u043a\\u0438 \\u043a\\u043e\\u0436\\u0443\\u0440\\u044b \\u043e\\u0441\\u0442\\u0430\\u044e\\u0442\\u0441\\u044f \\u0432 \\u0444\\u0438\\u043b\\u044c\\u0442\\u0440\\u0435.\",\"dignity\":\"\",\"shortcomings\":\"\",\"positive\":\"0\",\"negative\":\"0\",\"replies\":[],\"marks\":[],\"questions\":[],\"created_iso\":\"2019-07-22T12:13:36+03:00\"}","is_vendor_comment":true,"vendor_logo":"https://i2.rozetka.ua/producers/9/9401.80x60.png"}]},"comments":[{"id":44381813,"usertitle":"Лилия Коновал","mark":5,"percent_dignity":"75","text":"","dignity":"Любимейший блендер. Арахис в пасту перемалывает","shortcomings":"","from_buyer":true,"created":{"pop_date":"20 сентября 2019","year":"2019","month":9,"day":"20"},"questions":{"combobox":[],"marks":[],"integer":[]},"attachments":[],"lightboxattachmentsjson":"[]","commentdatajson":{"id":44381813,"goods_id":"17406357","user_title":"Лилия Коновал","created":"20 сентября 2019","from_buyer":true,"mark":5,"text":"","dignity":"Любимейший блендер. Арахис в пасту перемалывает","shortcomings":"","positive":"3","negative":"1","replies":[],"marks":[],"questions":[],"created_iso":"2019-09-20T16:12:00+03:00"},"is_vendor_comment":false,"vendor_logo":"","seller_id":5,"replies":[],"mark_percent":"100%","votes":{"positive":3,"negative":1,"total":4}},{"id":44145632,"usertitle":"Юлия Шило","mark":0,"percent_dignity":"100","text":"я немного не поняла, га сайте Филипс эта модель представлена как Viva Collection","dignity":"","shortcomings":"","from_buyer":false,"created":{"pop_date":"15 августа 2019","year":"2019","month":8,"day":"15"},"questions":{"combobox":[],"marks":[],"integer":[]},"attachments":[],"lightboxattachmentsjson":"[]","commentdatajson":{"id":44145632,"goods_id":"17406357","user_title":"Юлия Шило","created":"15 августа 2019","from_buyer":false,"mark":0,"text":"я немного не поняла, га сайте Филипс эта модель представлена как Viva Collection","dignity":"","shortcomings":"","positive":"1","negative":"0","replies":[],"marks":[],"questions":[],"created_iso":"2019-08-15T18:11:43+03:00"},"is_vendor_comment":false,"vendor_logo":"","seller_id":5,"replies":[],"mark_percent":"0%","votes":{"positive":1,"negative":0,"total":1}},{"id":44010025,"usertitle":"Мифтахова Карина","mark":0,"percent_dignity":"0","text":"Возможно ли в этом блендере делать ореховое молоко( кокосвое миндальное и кунжутное) с добавлением воды??? Заранее благодарю.","dignity":"","shortcomings":"","from_buyer":false,"created":{"pop_date":"22 июля 2019","year":"2019","month":7,"day":"22"},"questions":{"combobox":[],"marks":[],"integer":[]},"attachments":[],"lightboxattachmentsjson":"[]","commentdatajson":{"id":44010025,"goods_id":"17406357","user_title":"Мифтахова Карина","created":"22 июля 2019","from_buyer":false,"mark":0,"text":"Возможно ли в этом блендере делать ореховое молоко( кокосвое миндальное и кунжутное) с добавлением воды??? Заранее благодарю.","dignity":"","shortcomings":"","positive":"0","negative":"0","replies":[{"created":"22 июля 2019","user_title":"Представитель компании Philips","text":"Добрый день, Карина! Благодарим Вас за вопрос. С помощью данной модели блендера Вы можете делать ореховое молоко с добавлением воды. Также Вы можете обратить внимание на блендер модели HR2103/00, комплектация которого включает в себя  фильтр для приготовления соевого молока и фруктового сока без косточек и семян, при приготовлении с помощью фильтра все зёрна и кусочки кожуры остаются в фильтре."}],"marks":[],"questions":[],"created_iso":"2019-07-22T00:21:58+03:00"},"is_vendor_comment":false,"vendor_logo":"","seller_id":5,"replies":[{"id":44011894,"usertitle":"Представитель компании Philips","mark":0,"percent_dignity":"0","count_voices":0,"count_positive_voices":0,"negative_vote_count":0,"text":"Добрый день, Карина! Благодарим Вас за вопрос. С помощью данной модели блендера Вы можете делать ореховое молоко с добавлением воды. Также Вы можете обратить внимание на блендер модели HR2103/00, комплектация которого включает в себя  фильтр для приготовления соевого молока и фруктового сока без косточек и семян, при приготовлении с помощью фильтра все зёрна и кусочки кожуры остаются в фильтре.","dignity":"","shortcomings":"","from_buyer":false,"created":{"pop_date":"22 июля 2019","year":"2019","month":7,"day":"22"},"questions":{"combobox":[],"marks":[],"integer":[]},"attachments":{"images":[],"video":[]},"lightboxattachmentsjson":"[]","commentdatajson":"{\"id\":44011894,\"goods_id\":\"17406357\",\"user_title\":\"\\u041f\\u0440\\u0435\\u0434\\u0441\\u0442\\u0430\\u0432\\u0438\\u0442\\u0435\\u043b\\u044c \\u043a\\u043e\\u043c\\u043f\\u0430\\u043d\\u0438\\u0438 Philips\",\"created\":\"22 \\u0438\\u044e\\u043b\\u044f 2019\",\"from_buyer\":false,\"mark\":0,\"text\":\"\\u0414\\u043e\\u0431\\u0440\\u044b\\u0439 \\u0434\\u0435\\u043d\\u044c, \\u041a\\u0430\\u0440\\u0438\\u043d\\u0430! \\u0411\\u043b\\u0430\\u0433\\u043e\\u0434\\u0430\\u0440\\u0438\\u043c \\u0412\\u0430\\u0441 \\u0437\\u0430 \\u0432\\u043e\\u043f\\u0440\\u043e\\u0441. \\u0421 \\u043f\\u043e\\u043c\\u043e\\u0449\\u044c\\u044e \\u0434\\u0430\\u043d\\u043d\\u043e\\u0439 \\u043c\\u043e\\u0434\\u0435\\u043b\\u0438 \\u0431\\u043b\\u0435\\u043d\\u0434\\u0435\\u0440\\u0430 \\u0412\\u044b \\u043c\\u043e\\u0436\\u0435\\u0442\\u0435 \\u0434\\u0435\\u043b\\u0430\\u0442\\u044c \\u043e\\u0440\\u0435\\u0445\\u043e\\u0432\\u043e\\u0435 \\u043c\\u043e\\u043b\\u043e\\u043a\\u043e \\u0441 \\u0434\\u043e\\u0431\\u0430\\u0432\\u043b\\u0435\\u043d\\u0438\\u0435\\u043c \\u0432\\u043e\\u0434\\u044b. \\u0422\\u0430\\u043a\\u0436\\u0435 \\u0412\\u044b \\u043c\\u043e\\u0436\\u0435\\u0442\\u0435 \\u043e\\u0431\\u0440\\u0430\\u0442\\u0438\\u0442\\u044c \\u0432\\u043d\\u0438\\u043c\\u0430\\u043d\\u0438\\u0435 \\u043d\\u0430 \\u0431\\u043b\\u0435\\u043d\\u0434\\u0435\\u0440 \\u043c\\u043e\\u0434\\u0435\\u043b\\u0438 HR2103\\/00, \\u043a\\u043e\\u043c\\u043f\\u043b\\u0435\\u043a\\u0442\\u0430\\u0446\\u0438\\u044f \\u043a\\u043e\\u0442\\u043e\\u0440\\u043e\\u0433\\u043e \\u0432\\u043a\\u043b\\u044e\\u0447\\u0430\\u0435\\u0442 \\u0432 \\u0441\\u0435\\u0431\\u044f  \\u0444\\u0438\\u043b\\u044c\\u0442\\u0440 \\u0434\\u043b\\u044f \\u043f\\u0440\\u0438\\u0433\\u043e\\u0442\\u043e\\u0432\\u043b\\u0435\\u043d\\u0438\\u044f \\u0441\\u043e\\u0435\\u0432\\u043e\\u0433\\u043e \\u043c\\u043e\\u043b\\u043e\\u043a\\u0430 \\u0438 \\u0444\\u0440\\u0443\\u043a\\u0442\\u043e\\u0432\\u043e\\u0433\\u043e \\u0441\\u043e\\u043a\\u0430 \\u0431\\u0435\\u0437 \\u043a\\u043e\\u0441\\u0442\\u043e\\u0447\\u0435\\u043a \\u0438 \\u0441\\u0435\\u043c\\u044f\\u043d, \\u043f\\u0440\\u0438 \\u043f\\u0440\\u0438\\u0433\\u043e\\u0442\\u043e\\u0432\\u043b\\u0435\\u043d\\u0438\\u0438 \\u0441 \\u043f\\u043e\\u043c\\u043e\\u0449\\u044c\\u044e \\u0444\\u0438\\u043b\\u044c\\u0442\\u0440\\u0430 \\u0432\\u0441\\u0435 \\u0437\\u0451\\u0440\\u043d\\u0430 \\u0438 \\u043a\\u0443\\u0441\\u043e\\u0447\\u043a\\u0438 \\u043a\\u043e\\u0436\\u0443\\u0440\\u044b \\u043e\\u0441\\u0442\\u0430\\u044e\\u0442\\u0441\\u044f \\u0432 \\u0444\\u0438\\u043b\\u044c\\u0442\\u0440\\u0435.\",\"dignity\":\"\",\"shortcomings\":\"\",\"positive\":\"0\",\"negative\":\"0\",\"replies\":[],\"marks\":[],\"questions\":[],\"created_iso\":\"2019-07-22T12:13:36+03:00\"}","is_vendor_comment":true,"vendor_logo":"https://i2.rozetka.ua/producers/9/9401.80x60.png"}],"mark_percent":"0%","votes":{"positive":0,"negative":0,"total":0}},{"id":43960927,"usertitle":"Тарас Бульба","mark":null,"percent_dignity":"0","text":"Підкажіть, будь ласка, з якого матеріалу зроблена пляшка, яка йде в комплекті з цим блендером?","dignity":"","shortcomings":"","from_buyer":false,"created":{"pop_date":"12 июля 2019","year":"2019","month":7,"day":"12"},"questions":{"combobox":[],"marks":[],"integer":[]},"attachments":[],"lightboxattachmentsjson":"[]","commentdatajson":{"id":43960927,"goods_id":"17406357","user_title":"Тарас Бульба","created":"12 июля 2019","from_buyer":false,"mark":null,"text":"Підкажіть, будь ласка, з якого матеріалу зроблена пляшка, яка йде в комплекті з цим блендером?","dignity":"","shortcomings":"","positive":"0","negative":"0","replies":[{"created":"17 июля 2019","user_title":"Представитель компании Philips","text":"Доброго дня, Тарасе! Дякуємо за Ваше запитання. Пляшка On the Go виготовлена з пластику."},{"created":"17 июля 2019","user_title":"Представитель компании Philips","text":"Доброго дня, Тарасе! Дякуємо за Ваше запитання. Пляшка On the Go виготовлена з пластику."}],"marks":[],"questions":[],"created_iso":"2019-07-12T13:48:16+03:00"},"is_vendor_comment":false,"vendor_logo":"","seller_id":5,"replies":[{"id":43988207,"usertitle":"Представитель компании Philips","mark":0,"percent_dignity":"0","count_voices":0,"count_positive_voices":0,"negative_vote_count":0,"text":"Доброго дня, Тарасе! Дякуємо за Ваше запитання. Пляшка On the Go виготовлена з пластику.","dignity":"","shortcomings":"","from_buyer":false,"created":{"pop_date":"17 июля 2019","year":"2019","month":7,"day":"17"},"questions":{"combobox":[],"marks":[],"integer":[]},"attachments":{"images":[],"video":[]},"lightboxattachmentsjson":"[]","commentdatajson":"{\"id\":43988207,\"goods_id\":\"17406357\",\"user_title\":\"\\u041f\\u0440\\u0435\\u0434\\u0441\\u0442\\u0430\\u0432\\u0438\\u0442\\u0435\\u043b\\u044c \\u043a\\u043e\\u043c\\u043f\\u0430\\u043d\\u0438\\u0438 Philips\",\"created\":\"17 \\u0438\\u044e\\u043b\\u044f 2019\",\"from_buyer\":false,\"mark\":0,\"text\":\"\\u0414\\u043e\\u0431\\u0440\\u043e\\u0433\\u043e \\u0434\\u043d\\u044f, \\u0422\\u0430\\u0440\\u0430\\u0441\\u0435! \\u0414\\u044f\\u043a\\u0443\\u0454\\u043c\\u043e \\u0437\\u0430 \\u0412\\u0430\\u0448\\u0435 \\u0437\\u0430\\u043f\\u0438\\u0442\\u0430\\u043d\\u043d\\u044f. \\u041f\\u043b\\u044f\\u0448\\u043a\\u0430 On the Go \\u0432\\u0438\\u0433\\u043e\\u0442\\u043e\\u0432\\u043b\\u0435\\u043d\\u0430 \\u0437 \\u043f\\u043b\\u0430\\u0441\\u0442\\u0438\\u043a\\u0443.\",\"dignity\":\"\",\"shortcomings\":\"\",\"positive\":\"0\",\"negative\":\"0\",\"replies\":[],\"marks\":[],\"questions\":[],\"created_iso\":\"2019-07-17T15:43:11+03:00\"}","is_vendor_comment":true,"vendor_logo":"https://i2.rozetka.ua/producers/9/9401.80x60.png"},{"id":43988208,"usertitle":"Представитель компании Philips","mark":0,"percent_dignity":"0","count_voices":0,"count_positive_voices":0,"negative_vote_count":0,"text":"Доброго дня, Тарасе! Дякуємо за Ваше запитання. Пляшка On the Go виготовлена з пластику.","dignity":"","shortcomings":"","from_buyer":false,"created":{"pop_date":"17 июля 2019","year":"2019","month":7,"day":"17"},"questions":{"combobox":[],"marks":[],"integer":[]},"attachments":{"images":[],"video":[]},"lightboxattachmentsjson":"[]","commentdatajson":"{\"id\":43988208,\"goods_id\":\"17406357\",\"user_title\":\"\\u041f\\u0440\\u0435\\u0434\\u0441\\u0442\\u0430\\u0432\\u0438\\u0442\\u0435\\u043b\\u044c \\u043a\\u043e\\u043c\\u043f\\u0430\\u043d\\u0438\\u0438 Philips\",\"created\":\"17 \\u0438\\u044e\\u043b\\u044f 2019\",\"from_buyer\":false,\"mark\":0,\"text\":\"\\u0414\\u043e\\u0431\\u0440\\u043e\\u0433\\u043e \\u0434\\u043d\\u044f, \\u0422\\u0430\\u0440\\u0430\\u0441\\u0435! \\u0414\\u044f\\u043a\\u0443\\u0454\\u043c\\u043e \\u0437\\u0430 \\u0412\\u0430\\u0448\\u0435 \\u0437\\u0430\\u043f\\u0438\\u0442\\u0430\\u043d\\u043d\\u044f. \\u041f\\u043b\\u044f\\u0448\\u043a\\u0430 On the Go \\u0432\\u0438\\u0433\\u043e\\u0442\\u043e\\u0432\\u043b\\u0435\\u043d\\u0430 \\u0437 \\u043f\\u043b\\u0430\\u0441\\u0442\\u0438\\u043a\\u0443.\",\"dignity\":\"\",\"shortcomings\":\"\",\"positive\":\"0\",\"negative\":\"0\",\"replies\":[],\"marks\":[],\"questions\":[],\"created_iso\":\"2019-07-17T15:43:17+03:00\"}","is_vendor_comment":true,"vendor_logo":"https://i2.rozetka.ua/producers/9/9401.80x60.png"}],"votes":{"positive":0,"negative":0,"total":0}},{"id":43121194,"usertitle":"Тарас Рудик","mark":0,"percent_dignity":"0","text":"Яка його потужність?  700вт. чи  900вт.","dignity":"","shortcomings":"","from_buyer":false,"created":{"pop_date":"10 июня 2019","year":"2019","month":6,"day":"10"},"questions":{"combobox":[],"marks":[],"integer":[]},"attachments":[],"lightboxattachmentsjson":"[]","commentdatajson":{"id":43121194,"goods_id":"17406357","user_title":"Тарас Рудик","created":"10 июня 2019","from_buyer":false,"mark":0,"text":"Яка його потужність?  700вт. чи  900вт.","dignity":"","shortcomings":"","positive":"0","negative":"0","replies":[{"created":"12 июня 2019","user_title":"Представитель компании Philips","text":"Добрий день, Тарасе! Потужність даної моделі блендера становить 900 Вт."}],"marks":[],"questions":[],"created_iso":"2019-06-10T10:50:52+03:00"},"is_vendor_comment":false,"vendor_logo":"","seller_id":5,"replies":[{"id":43211266,"usertitle":"Представитель компании Philips","mark":0,"percent_dignity":"0","count_voices":0,"count_positive_voices":0,"negative_vote_count":0,"text":"Добрий день, Тарасе! Потужність даної моделі блендера становить 900 Вт.","dignity":"","shortcomings":"","from_buyer":false,"created":{"pop_date":"12 июня 2019","year":"2019","month":6,"day":"12"},"questions":{"combobox":[],"marks":[],"integer":[]},"attachments":{"images":[],"video":[]},"lightboxattachmentsjson":"[]","commentdatajson":"{\"id\":43211266,\"goods_id\":\"17406357\",\"user_title\":\"\\u041f\\u0440\\u0435\\u0434\\u0441\\u0442\\u0430\\u0432\\u0438\\u0442\\u0435\\u043b\\u044c \\u043a\\u043e\\u043c\\u043f\\u0430\\u043d\\u0438\\u0438 Philips\",\"created\":\"12 \\u0438\\u044e\\u043d\\u044f 2019\",\"from_buyer\":false,\"mark\":0,\"text\":\"\\u0414\\u043e\\u0431\\u0440\\u0438\\u0439 \\u0434\\u0435\\u043d\\u044c, \\u0422\\u0430\\u0440\\u0430\\u0441\\u0435! \\u041f\\u043e\\u0442\\u0443\\u0436\\u043d\\u0456\\u0441\\u0442\\u044c \\u0434\\u0430\\u043d\\u043e\\u0457 \\u043c\\u043e\\u0434\\u0435\\u043b\\u0456 \\u0431\\u043b\\u0435\\u043d\\u0434\\u0435\\u0440\\u0430 \\u0441\\u0442\\u0430\\u043d\\u043e\\u0432\\u0438\\u0442\\u044c 900 \\u0412\\u0442.\",\"dignity\":\"\",\"shortcomings\":\"\",\"positive\":\"0\",\"negative\":\"0\",\"replies\":[],\"marks\":[],\"questions\":[],\"created_iso\":\"2019-06-12T15:09:18+03:00\"}","is_vendor_comment":true,"vendor_logo":"https://i2.rozetka.ua/producers/9/9401.80x60.png"}],"mark_percent":"0%","votes":{"positive":0,"negative":0,"total":0}},{"id":42069166,"usertitle":"Alexander","mark":0,"percent_dignity":"80","text":"Никак не могу понять, твердые продукты ставить нельзя, но колка льда есть, поясните пожалуйста.","dignity":"","shortcomings":"","from_buyer":true,"created":{"pop_date":"10 мая 2019","year":"2019","month":5,"day":"10"},"questions":{"combobox":[],"marks":[],"integer":[]},"attachments":[],"lightboxattachmentsjson":"[]","commentdatajson":{"id":42069166,"goods_id":"17406357","user_title":"Alexander","created":"10 мая 2019","from_buyer":true,"mark":0,"text":"Никак не могу понять, твердые продукты ставить нельзя, но колка льда есть, поясните пожалуйста.","dignity":"","shortcomings":"","positive":"4","negative":"1","replies":[{"created":"21 мая 2019","user_title":"Представитель компании Philips","text":"Добрый день, Александр! С помощью данного блендера можно обрабатывать сырые, твердые овощи (например морковь), но обращаем Ваше внимание на то, что при измельчении такого рода продуктов необходимо доливать немного воды."}],"marks":[],"questions":[],"created_iso":"2019-05-10T08:13:58+03:00"},"is_vendor_comment":false,"vendor_logo":"","seller_id":5,"replies":[{"id":42478490,"usertitle":"Представитель компании Philips","mark":0,"percent_dignity":"0","count_voices":0,"count_positive_voices":0,"negative_vote_count":0,"text":"Добрый день, Александр! С помощью данного блендера можно обрабатывать сырые, твердые овощи (например морковь), но обращаем Ваше внимание на то, что при измельчении такого рода продуктов необходимо доливать немного воды.","dignity":"","shortcomings":"","from_buyer":false,"created":{"pop_date":"21 мая 2019","year":"2019","month":5,"day":"21"},"questions":{"combobox":[],"marks":[],"integer":[]},"attachments":{"images":[],"video":[]},"lightboxattachmentsjson":"[]","commentdatajson":"{\"id\":42478490,\"goods_id\":\"17406357\",\"user_title\":\"\\u041f\\u0440\\u0435\\u0434\\u0441\\u0442\\u0430\\u0432\\u0438\\u0442\\u0435\\u043b\\u044c \\u043a\\u043e\\u043c\\u043f\\u0430\\u043d\\u0438\\u0438 Philips\",\"created\":\"21 \\u043c\\u0430\\u044f 2019\",\"from_buyer\":false,\"mark\":0,\"text\":\"\\u0414\\u043e\\u0431\\u0440\\u044b\\u0439 \\u0434\\u0435\\u043d\\u044c, \\u0410\\u043b\\u0435\\u043a\\u0441\\u0430\\u043d\\u0434\\u0440! \\u0421 \\u043f\\u043e\\u043c\\u043e\\u0449\\u044c\\u044e \\u0434\\u0430\\u043d\\u043d\\u043e\\u0433\\u043e \\u0431\\u043b\\u0435\\u043d\\u0434\\u0435\\u0440\\u0430 \\u043c\\u043e\\u0436\\u043d\\u043e \\u043e\\u0431\\u0440\\u0430\\u0431\\u0430\\u0442\\u044b\\u0432\\u0430\\u0442\\u044c \\u0441\\u044b\\u0440\\u044b\\u0435, \\u0442\\u0432\\u0435\\u0440\\u0434\\u044b\\u0435 \\u043e\\u0432\\u043e\\u0449\\u0438 (\\u043d\\u0430\\u043f\\u0440\\u0438\\u043c\\u0435\\u0440 \\u043c\\u043e\\u0440\\u043a\\u043e\\u0432\\u044c), \\u043d\\u043e \\u043e\\u0431\\u0440\\u0430\\u0449\\u0430\\u0435\\u043c \\u0412\\u0430\\u0448\\u0435 \\u0432\\u043d\\u0438\\u043c\\u0430\\u043d\\u0438\\u0435 \\u043d\\u0430 \\u0442\\u043e, \\u0447\\u0442\\u043e \\u043f\\u0440\\u0438 \\u0438\\u0437\\u043c\\u0435\\u043b\\u044c\\u0447\\u0435\\u043d\\u0438\\u0438 \\u0442\\u0430\\u043a\\u043e\\u0433\\u043e \\u0440\\u043e\\u0434\\u0430 \\u043f\\u0440\\u043e\\u0434\\u0443\\u043a\\u0442\\u043e\\u0432 \\u043d\\u0435\\u043e\\u0431\\u0445\\u043e\\u0434\\u0438\\u043c\\u043e \\u0434\\u043e\\u043b\\u0438\\u0432\\u0430\\u0442\\u044c \\u043d\\u0435\\u043c\\u043d\\u043e\\u0433\\u043e \\u0432\\u043e\\u0434\\u044b.\",\"dignity\":\"\",\"shortcomings\":\"\",\"positive\":\"0\",\"negative\":\"0\",\"replies\":[],\"marks\":[],\"questions\":[],\"created_iso\":\"2019-05-21T14:40:45+03:00\"}","is_vendor_comment":true,"vendor_logo":"https://i2.rozetka.ua/producers/9/9401.80x60.png"}],"mark_percent":"0%","votes":{"positive":4,"negative":1,"total":5}},{"id":42033598,"usertitle":"Дмитрий","mark":0,"percent_dignity":"67","text":"Здравствуйте, подскажите можно ли в этом блендере взбивать яблоки, морковку, огурцы и прочие твёрдые фрукты/овощи?","dignity":"","shortcomings":"","from_buyer":false,"created":{"pop_date":"8 мая 2019","year":"2019","month":5,"day":"08"},"questions":{"combobox":[],"marks":[],"integer":[]},"attachments":[],"lightboxattachmentsjson":"[]","commentdatajson":{"id":42033598,"goods_id":"17406357","user_title":"Дмитрий","created":"8 мая 2019","from_buyer":false,"mark":0,"text":"Здравствуйте, подскажите можно ли в этом блендере взбивать яблоки, морковку, огурцы и прочие твёрдые фрукты/овощи?","dignity":"","shortcomings":"","positive":"2","negative":"1","replies":[{"created":"9 мая 2019","user_title":"Валя","text":"ниже отвечал представитель, <br />\n Согласно инструкции по эксплуатации, чаша блендера предназначена для: <br />\n- Перемешивания жидкостей, таких как молочные продукты, соусы, фруктовые соки, супы, напитки, коктейли, смузи.<br />\n- Перемешивания мягких продуктов, таких как жидкое тесто или майонез.<br />\n- Приготовления пюре из отварных продуктов, например, приготовления детского питания.<br />\n- Измельчения кубиков льда."}],"marks":[],"questions":[],"created_iso":"2019-05-08T22:44:25+03:00"},"is_vendor_comment":false,"vendor_logo":"","seller_id":5,"replies":[{"id":42038812,"usertitle":"Валя","mark":0,"percent_dignity":"0","count_voices":0,"count_positive_voices":0,"negative_vote_count":0,"text":"ниже отвечал представитель, <br />\n Согласно инструкции по эксплуатации, чаша блендера предназначена для: <br />\n- Перемешивания жидкостей, таких как молочные продукты, соусы, фруктовые соки, супы, напитки, коктейли, смузи.<br />\n- Перемешивания мягких продуктов, таких как жидкое тесто или майонез.<br />\n- Приготовления пюре из отварных продуктов, например, приготовления детского питания.<br />\n- Измельчения кубиков льда.","dignity":"","shortcomings":"","from_buyer":false,"created":{"pop_date":"9 мая 2019","year":"2019","month":5,"day":"09"},"questions":{"combobox":[],"marks":[],"integer":[]},"attachments":{"images":[],"video":[]},"lightboxattachmentsjson":"[]","commentdatajson":"{\"id\":42038812,\"goods_id\":\"17406357\",\"user_title\":\"\\u0412\\u0430\\u043b\\u044f\",\"created\":\"9 \\u043c\\u0430\\u044f 2019\",\"from_buyer\":false,\"mark\":0,\"text\":\"\\u043d\\u0438\\u0436\\u0435 \\u043e\\u0442\\u0432\\u0435\\u0447\\u0430\\u043b \\u043f\\u0440\\u0435\\u0434\\u0441\\u0442\\u0430\\u0432\\u0438\\u0442\\u0435\\u043b\\u044c, <br \\/>\\n \\u0421\\u043e\\u0433\\u043b\\u0430\\u0441\\u043d\\u043e \\u0438\\u043d\\u0441\\u0442\\u0440\\u0443\\u043a\\u0446\\u0438\\u0438 \\u043f\\u043e \\u044d\\u043a\\u0441\\u043f\\u043b\\u0443\\u0430\\u0442\\u0430\\u0446\\u0438\\u0438, \\u0447\\u0430\\u0448\\u0430 \\u0431\\u043b\\u0435\\u043d\\u0434\\u0435\\u0440\\u0430 \\u043f\\u0440\\u0435\\u0434\\u043d\\u0430\\u0437\\u043d\\u0430\\u0447\\u0435\\u043d\\u0430 \\u0434\\u043b\\u044f: <br \\/>\\n- \\u041f\\u0435\\u0440\\u0435\\u043c\\u0435\\u0448\\u0438\\u0432\\u0430\\u043d\\u0438\\u044f \\u0436\\u0438\\u0434\\u043a\\u043e\\u0441\\u0442\\u0435\\u0439, \\u0442\\u0430\\u043a\\u0438\\u0445 \\u043a\\u0430\\u043a \\u043c\\u043e\\u043b\\u043e\\u0447\\u043d\\u044b\\u0435 \\u043f\\u0440\\u043e\\u0434\\u0443\\u043a\\u0442\\u044b, \\u0441\\u043e\\u0443\\u0441\\u044b, \\u0444\\u0440\\u0443\\u043a\\u0442\\u043e\\u0432\\u044b\\u0435 \\u0441\\u043e\\u043a\\u0438, \\u0441\\u0443\\u043f\\u044b, \\u043d\\u0430\\u043f\\u0438\\u0442\\u043a\\u0438, \\u043a\\u043e\\u043a\\u0442\\u0435\\u0439\\u043b\\u0438, \\u0441\\u043c\\u0443\\u0437\\u0438.<br \\/>\\n- \\u041f\\u0435\\u0440\\u0435\\u043c\\u0435\\u0448\\u0438\\u0432\\u0430\\u043d\\u0438\\u044f \\u043c\\u044f\\u0433\\u043a\\u0438\\u0445 \\u043f\\u0440\\u043e\\u0434\\u0443\\u043a\\u0442\\u043e\\u0432, \\u0442\\u0430\\u043a\\u0438\\u0445 \\u043a\\u0430\\u043a \\u0436\\u0438\\u0434\\u043a\\u043e\\u0435 \\u0442\\u0435\\u0441\\u0442\\u043e \\u0438\\u043b\\u0438 \\u043c\\u0430\\u0439\\u043e\\u043d\\u0435\\u0437.<br \\/>\\n- \\u041f\\u0440\\u0438\\u0433\\u043e\\u0442\\u043e\\u0432\\u043b\\u0435\\u043d\\u0438\\u044f \\u043f\\u044e\\u0440\\u0435 \\u0438\\u0437 \\u043e\\u0442\\u0432\\u0430\\u0440\\u043d\\u044b\\u0445 \\u043f\\u0440\\u043e\\u0434\\u0443\\u043a\\u0442\\u043e\\u0432, \\u043d\\u0430\\u043f\\u0440\\u0438\\u043c\\u0435\\u0440, \\u043f\\u0440\\u0438\\u0433\\u043e\\u0442\\u043e\\u0432\\u043b\\u0435\\u043d\\u0438\\u044f \\u0434\\u0435\\u0442\\u0441\\u043a\\u043e\\u0433\\u043e \\u043f\\u0438\\u0442\\u0430\\u043d\\u0438\\u044f.<br \\/>\\n- \\u0418\\u0437\\u043c\\u0435\\u043b\\u044c\\u0447\\u0435\\u043d\\u0438\\u044f \\u043a\\u0443\\u0431\\u0438\\u043a\\u043e\\u0432 \\u043b\\u044c\\u0434\\u0430.\",\"dignity\":\"\",\"shortcomings\":\"\",\"positive\":\"0\",\"negative\":\"0\",\"replies\":[],\"marks\":[],\"questions\":[],\"created_iso\":\"2019-05-09T09:09:00+03:00\"}","is_vendor_comment":false,"vendor_logo":""}],"mark_percent":"0%","votes":{"positive":2,"negative":1,"total":3}},{"id":41841426,"usertitle":"Тарас Ми","mark":0,"percent_dignity":"100","text":"Представнику Philips. аксесуар CP6670 підійде до данної моделі блендера?","dignity":"","shortcomings":"","from_buyer":false,"created":{"pop_date":"3 мая 2019","year":"2019","month":5,"day":"03"},"questions":{"combobox":[],"marks":[],"integer":[]},"attachments":[],"lightboxattachmentsjson":"[]","commentdatajson":{"id":41841426,"goods_id":"17406357","user_title":"Тарас Ми","created":"3 мая 2019","from_buyer":false,"mark":0,"text":"Представнику Philips. аксесуар CP6670 підійде до данної моделі блендера?","dignity":"","shortcomings":"","positive":"1","negative":"0","replies":[{"created":"13 мая 2019","user_title":"Представитель компании Philips","text":"Доброго дня, Тарасе! Так, аксесуар моделі CP6670, згідно з інструкцією, підходить для даної моделі блендера (https://www.download.p4c.philips.com/files/h/hr3556_00/hr3556_00_dfu_ukr.pdf)."}],"marks":[],"questions":[],"created_iso":"2019-05-03T21:47:06+03:00"},"is_vendor_comment":false,"vendor_logo":"","seller_id":5,"replies":[{"id":42191865,"usertitle":"Представитель компании Philips","mark":0,"percent_dignity":"0","count_voices":0,"count_positive_voices":0,"negative_vote_count":0,"text":"Доброго дня, Тарасе! Так, аксесуар моделі CP6670, згідно з інструкцією, підходить для даної моделі блендера (https://www.download.p4c.philips.com/files/h/hr3556_00/hr3556_00_dfu_ukr.pdf).","dignity":"","shortcomings":"","from_buyer":false,"created":{"pop_date":"13 мая 2019","year":"2019","month":5,"day":"13"},"questions":{"combobox":[],"marks":[],"integer":[]},"attachments":{"images":[],"video":[]},"lightboxattachmentsjson":"[]","commentdatajson":"{\"id\":42191865,\"goods_id\":\"17406357\",\"user_title\":\"\\u041f\\u0440\\u0435\\u0434\\u0441\\u0442\\u0430\\u0432\\u0438\\u0442\\u0435\\u043b\\u044c \\u043a\\u043e\\u043c\\u043f\\u0430\\u043d\\u0438\\u0438 Philips\",\"created\":\"13 \\u043c\\u0430\\u044f 2019\",\"from_buyer\":false,\"mark\":0,\"text\":\"\\u0414\\u043e\\u0431\\u0440\\u043e\\u0433\\u043e \\u0434\\u043d\\u044f, \\u0422\\u0430\\u0440\\u0430\\u0441\\u0435! \\u0422\\u0430\\u043a, \\u0430\\u043a\\u0441\\u0435\\u0441\\u0443\\u0430\\u0440 \\u043c\\u043e\\u0434\\u0435\\u043b\\u0456 CP6670, \\u0437\\u0433\\u0456\\u0434\\u043d\\u043e \\u0437 \\u0456\\u043d\\u0441\\u0442\\u0440\\u0443\\u043a\\u0446\\u0456\\u0454\\u044e, \\u043f\\u0456\\u0434\\u0445\\u043e\\u0434\\u0438\\u0442\\u044c \\u0434\\u043b\\u044f \\u0434\\u0430\\u043d\\u043e\\u0457 \\u043c\\u043e\\u0434\\u0435\\u043b\\u0456 \\u0431\\u043b\\u0435\\u043d\\u0434\\u0435\\u0440\\u0430 (https:\\/\\/www.download.p4c.philips.com\\/files\\/h\\/hr3556_00\\/hr3556_00_dfu_ukr.pdf).\",\"dignity\":\"\",\"shortcomings\":\"\",\"positive\":\"0\",\"negative\":\"0\",\"replies\":[],\"marks\":[],\"questions\":[],\"created_iso\":\"2019-05-13T14:01:00+03:00\"}","is_vendor_comment":true,"vendor_logo":"https://i2.rozetka.ua/producers/9/9401.80x60.png"}],"mark_percent":"0%","votes":{"positive":1,"negative":0,"total":1}},{"id":40045728,"usertitle":"Тая","mark":0,"percent_dignity":"75","text":"Взбивает замороженные бананы и ягоды?","dignity":"","shortcomings":"","from_buyer":false,"created":{"pop_date":"14 марта 2019","year":"2019","month":3,"day":"14"},"questions":{"combobox":[],"marks":[],"integer":[]},"attachments":[],"lightboxattachmentsjson":"[]","commentdatajson":{"id":40045728,"goods_id":"17406357","user_title":"Тая","created":"14 марта 2019","from_buyer":false,"mark":0,"text":"Взбивает замороженные бананы и ягоды?","dignity":"","shortcomings":"","positive":"3","negative":"1","replies":[{"created":"25 марта 2019","user_title":"Представитель компании Philips","text":"Добрый день, Тая! Благодарим Вас за вопрос. В данном блендере присутствует функция колки льда, поэтому с его помощью Вы можете обрабатывать замороженные фрукты."},{"created":"10 апреля 2019","user_title":"Вільвєталь Віайпі","text":"Дуже гарно вбиває усі ягоди окрім вовчих та собачих для таких придивітся краще до моделі Philips Avance Collection HR3652/00."}],"marks":[],"questions":[],"created_iso":"2019-03-14T21:00:53+02:00"},"is_vendor_comment":false,"vendor_logo":"","seller_id":5,"replies":[{"id":40464398,"usertitle":"Представитель компании Philips","mark":0,"percent_dignity":"0","count_voices":0,"count_positive_voices":0,"negative_vote_count":0,"text":"Добрый день, Тая! Благодарим Вас за вопрос. В данном блендере присутствует функция колки льда, поэтому с его помощью Вы можете обрабатывать замороженные фрукты.","dignity":"","shortcomings":"","from_buyer":false,"created":{"pop_date":"25 марта 2019","year":"2019","month":3,"day":"25"},"questions":{"combobox":[],"marks":[],"integer":[]},"attachments":{"images":[],"video":[]},"lightboxattachmentsjson":"[]","commentdatajson":"{\"id\":40464398,\"goods_id\":\"17406357\",\"user_title\":\"\\u041f\\u0440\\u0435\\u0434\\u0441\\u0442\\u0430\\u0432\\u0438\\u0442\\u0435\\u043b\\u044c \\u043a\\u043e\\u043c\\u043f\\u0430\\u043d\\u0438\\u0438 Philips\",\"created\":\"25 \\u043c\\u0430\\u0440\\u0442\\u0430 2019\",\"from_buyer\":false,\"mark\":0,\"text\":\"\\u0414\\u043e\\u0431\\u0440\\u044b\\u0439 \\u0434\\u0435\\u043d\\u044c, \\u0422\\u0430\\u044f! \\u0411\\u043b\\u0430\\u0433\\u043e\\u0434\\u0430\\u0440\\u0438\\u043c \\u0412\\u0430\\u0441 \\u0437\\u0430 \\u0432\\u043e\\u043f\\u0440\\u043e\\u0441. \\u0412 \\u0434\\u0430\\u043d\\u043d\\u043e\\u043c \\u0431\\u043b\\u0435\\u043d\\u0434\\u0435\\u0440\\u0435 \\u043f\\u0440\\u0438\\u0441\\u0443\\u0442\\u0441\\u0442\\u0432\\u0443\\u0435\\u0442 \\u0444\\u0443\\u043d\\u043a\\u0446\\u0438\\u044f \\u043a\\u043e\\u043b\\u043a\\u0438 \\u043b\\u044c\\u0434\\u0430, \\u043f\\u043e\\u044d\\u0442\\u043e\\u043c\\u0443 \\u0441 \\u0435\\u0433\\u043e \\u043f\\u043e\\u043c\\u043e\\u0449\\u044c\\u044e \\u0412\\u044b \\u043c\\u043e\\u0436\\u0435\\u0442\\u0435 \\u043e\\u0431\\u0440\\u0430\\u0431\\u0430\\u0442\\u044b\\u0432\\u0430\\u0442\\u044c \\u0437\\u0430\\u043c\\u043e\\u0440\\u043e\\u0436\\u0435\\u043d\\u043d\\u044b\\u0435 \\u0444\\u0440\\u0443\\u043a\\u0442\\u044b.\",\"dignity\":\"\",\"shortcomings\":\"\",\"positive\":\"0\",\"negative\":\"0\",\"replies\":[],\"marks\":[],\"questions\":[],\"created_iso\":\"2019-03-25T14:52:05+02:00\"}","is_vendor_comment":true,"vendor_logo":"https://i2.rozetka.ua/producers/9/9401.80x60.png"},{"id":41078781,"usertitle":"Вільвєталь Віайпі","mark":0,"percent_dignity":"0","count_voices":0,"count_positive_voices":0,"negative_vote_count":0,"text":"Дуже гарно вбиває усі ягоди окрім вовчих та собачих для таких придивітся краще до моделі Philips Avance Collection HR3652/00.","dignity":"","shortcomings":"","from_buyer":true,"created":{"pop_date":"10 апреля 2019","year":"2019","month":4,"day":"10"},"questions":{"combobox":[],"marks":[],"integer":[]},"attachments":{"images":[],"video":[]},"lightboxattachmentsjson":"[]","commentdatajson":"{\"id\":41078781,\"goods_id\":\"17406357\",\"user_title\":\"\\u0412\\u0456\\u043b\\u044c\\u0432\\u0454\\u0442\\u0430\\u043b\\u044c \\u0412\\u0456\\u0430\\u0439\\u043f\\u0456\",\"created\":\"10 \\u0430\\u043f\\u0440\\u0435\\u043b\\u044f 2019\",\"from_buyer\":true,\"mark\":0,\"text\":\"\\u0414\\u0443\\u0436\\u0435 \\u0433\\u0430\\u0440\\u043d\\u043e \\u0432\\u0431\\u0438\\u0432\\u0430\\u0454 \\u0443\\u0441\\u0456 \\u044f\\u0433\\u043e\\u0434\\u0438 \\u043e\\u043a\\u0440\\u0456\\u043c \\u0432\\u043e\\u0432\\u0447\\u0438\\u0445 \\u0442\\u0430 \\u0441\\u043e\\u0431\\u0430\\u0447\\u0438\\u0445 \\u0434\\u043b\\u044f \\u0442\\u0430\\u043a\\u0438\\u0445 \\u043f\\u0440\\u0438\\u0434\\u0438\\u0432\\u0456\\u0442\\u0441\\u044f \\u043a\\u0440\\u0430\\u0449\\u0435 \\u0434\\u043e \\u043c\\u043e\\u0434\\u0435\\u043b\\u0456 Philips Avance Collection HR3652\\/00.\",\"dignity\":\"\",\"shortcomings\":\"\",\"positive\":\"0\",\"negative\":\"0\",\"replies\":[],\"marks\":[],\"questions\":[],\"created_iso\":\"2019-04-10T16:23:31+03:00\"}","is_vendor_comment":false,"vendor_logo":""}],"mark_percent":"0%","votes":{"positive":3,"negative":1,"total":4}},{"id":39962496,"usertitle":"Юлия","mark":5,"percent_dignity":"0","text":"Очень классный блендер, пока мало использовали, но для смузи супер. Быстра доставка, заказывали курьера под дом. Пока что никаких нареканий нет. При первом использовании был характерный запах резины, но после ушёл и не появляется.","dignity":"Быстро измельчает, большой объём стакана","shortcomings":"Тяжеловатый стакан, но понимаю, что это плюс, ведь стекло лучше пластика в такой вещи. Пока нареканий нет","from_buyer":true,"created":{"pop_date":"12 марта 2019","year":"2019","month":3,"day":"12"},"questions":{"combobox":[],"marks":[],"integer":[]},"attachments":[],"lightboxattachmentsjson":"[]","commentdatajson":{"id":39962496,"goods_id":"17406357","user_title":"Юлия","created":"12 марта 2019","from_buyer":true,"mark":5,"text":"Очень классный блендер, пока мало использовали, но для смузи супер. Быстра доставка, заказывали курьера под дом. Пока что никаких нареканий нет. При первом использовании был характерный запах резины, но после ушёл и не появляется.","dignity":"Быстро измельчает, большой объём стакана","shortcomings":"Тяжеловатый стакан, но понимаю, что это плюс, ведь стекло лучше пластика в такой вещи. Пока нареканий нет","positive":"0","negative":"0","replies":[],"marks":[],"questions":[],"created_iso":"2019-03-12T23:05:07+02:00"},"is_vendor_comment":false,"vendor_logo":"","seller_id":5,"replies":[],"mark_percent":"100%","votes":{"positive":0,"negative":0,"total":0}}],"most_useful":[],"questions":{"marks":[],"combobox":[]},"form_focus":false,"complaints_reasons":[{"title":"нецензурная лексика, оскорбление или агрессия","id":1},{"title":"явная реклама (спам)","id":3},{"title":"ссылки на незаконные сайты и программы","id":2},{"title":"не относится к обсуждаемой теме","id":4},{"title":"другая причина","id":5}],"gallery_data":{"attachments":[{"comment_id":24869567,"original":{"src":"https://comments-images.rozetka.com.ua/goods_comments/0/0/1/749/1749839.jpg","width":960,"height":720},"big":{"src":"https://comments-images.rozetka.com.ua/goods_comments/0/0/1/749/1749839.675x532.jpg","width":675,"height":532},"preview":{"src":"https://comments-images.rozetka.com.ua/goods_comments/0/0/1/749/1749839.256x256.jpg","width":256,"height":256}},{"comment_id":45401535,"embed_url":"https://www.youtube.com/v/48LwY2m2rqg?color1=&color2=&hl=&fs=&enablejsapi=1&","ext_video_id":"48LwY2m2rqg","id":470760,"width":480,"height":270,"is_mpeg4":false,"type":"youtube","url":"https://youtu.be/48LwY2m2rqg","presentation_type":"video","original":{"src":"https://i.ytimg.com/vi/48LwY2m2rqg/hqdefault.jpg#45401535","width":480,"height":270},"big":{"src":"https://i.ytimg.com/vi/48LwY2m2rqg/hqdefault.jpg#45401535","width":256,"height":256},"preview":{"src":"https://i.ytimg.com/vi/48LwY2m2rqg/hqdefault.jpg#45401535","width":256,"height":256},"params":[]},{"comment_id":45851941,"original":{"src":"https://comments-images.rozetka.com.ua/goods_comments/0/0/7/735/7735607.jpg","width":1537,"height":2090},"big":{"src":"https://comments-images.rozetka.com.ua/goods_comments/0/0/7/735/7735607.675x532.jpg","width":675,"height":532},"preview":{"src":"https://comments-images.rozetka.com.ua/goods_comments/0/0/7/735/7735607.256x256.jpg","width":256,"height":256}},{"comment_id":45851941,"original":{"src":"https://comments-images.rozetka.com.ua/goods_comments/0/0/7/735/7735608.jpg","width":1536,"height":2048},"big":{"src":"https://comments-images.rozetka.com.ua/goods_comments/0/0/7/735/7735608.675x532.jpg","width":675,"height":532},"preview":{"src":"https://comments-images.rozetka.com.ua/goods_comments/0/0/7/735/7735608.256x256.jpg","width":256,"height":256}}],"comments":[{"id":24869567,"goods_id":"17406357","user_title":"Андрей","created":"25 января 2018","from_buyer":true,"mark":2,"text":"Два раз включали, на третий включаться отказался. <br />\nДыма не было, ничего не расплавилось и не сгорело. Взбивал молочную кашу на малой скорости. Отключился и с концами. Отличное качество филипс. 100 баксов. Покупайте.","dignity":"Мощный и красивый","shortcomings":"Недолговечный","positive":"3","negative":"0","replies":[{"created":"25 января 2018","user_title":"Гость","text":"Там гарантия есть..."},{"created":"26 января 2018","user_title":"Представитель компании Philips","text":"Добрый день, Андрей! Благодарим Вас за отзыв и сожалеем о Вашем опыте использования блендера. В описанной Вами ситуации для диагностики прибора рекомендуем обратиться в сервисный центр компании Philips в Вашем городе, адрес которого Вы можете найти по следующей ссылке: http://philips.to/1WVbg0A . Для обращения в сервисный центр Вам понадобятся гарантийный талон, чек, подтверждающий покупку, а также документ удостоверяющий личность (для регистрации обращения)."}],"marks":[],"questions":[],"created_iso":"2018-01-25T14:49:07+02:00"},{"id":45401535,"goods_id":"17406357","user_title":"Lorellin","created":"5 февраля 2020","from_buyer":true,"mark":5,"text":"Искала блендер, который превращал бы продукты в гомогенное пюре, особенно морковь - и очень рада, что этот блендер с таким справляется! Он немного более шумный, чем другие блендеры (уровень их шума все-таки имеет значение при выборе), но в разы лучше, чем в бывает в других моделях. Удобно, что есть две емкости и два ножа, они немного отличаются друг от друга. Осваиваю и радуюсь :) <br />\nУдобно пользоваться импульсным режимом. В обзоре сняла то, что смотрела при тестах - как он делает вихрь в воде в разных чашках, какое получается пюре из яблок, моркови и банана. #мояраспаковка","dignity":"хорошо пюрирует, две емкости и ножа, чашка с собой","shortcomings":"немного шумный, цена","positive":"4","negative":"0","replies":[],"marks":[],"questions":[],"created_iso":"2020-02-05T10:00:10+02:00"},{"id":45851941,"goods_id":"17406357","user_title":"Lyuba","created":"31 марта 2020","from_buyer":false,"mark":5,"text":"Покупала 1,5 года назад! Очень пригодился мне при прохождении детокс программы! Где очень много блюд в виде пюре! Делала пюре из отварных овощей, мяса и бульона! И мы скидывали в общую группу детокса блюда! Мои выглядели аппетитнее всего ! Пюре однородное получалось, без комочков.. как из ресторана, а у других даже выглядело не аппетитно.. куски были и жидкость отдельно! Так что детокс я прошла без напряга!<br />\nЕщё детям делаю часто крем из творога, банана и йогурта и перемазываю им панкейки, как тортик . И очень вкусное пюре получается из запечённых яблок, как из баночки <br />\nМощность супер! Я очень довольна и дети тоже! Что немаловажно","dignity":"Гладкая и однородная консистенция пюре! Стеклянная чаша!","shortcomings":"Нет","positive":"1","negative":"0","replies":[],"marks":[],"questions":[],"created_iso":"2020-03-31T16:49:00+03:00"}]}}}